ldapauthenticator/__init__.py
ldapauthenticator/ldapauthenticator.py
jupyterhub_ldapauthenticator-2.0.2.dist-info/LICENSE
jupyterhub_ldapauthenticator-2.0.2.dist-info/METADATA
jupyterhub_ldapauthenticator-2.0.2.dist-info/WHEEL
jupyterhub_ldapauthenticator-2.0.2.dist-info/entry_points.txt
jupyterhub_ldapauthenticator-2.0.2.dist-info/top_level.txt
jupyterhub_ldapauthenticator-2.0.2.dist-info/RECORD
