Metadata-Version: 2.1
Name: jupyterhub-ldapauthenticator
Version: 2.0.2
Summary: LDAP Authenticator for JupyterHub
Home-page: https://github.com/jupyterhub/ldapauthenticator
Author: Yuvi Panda
Author-email: yuvipanda@riseup.net
License: 3 Clause BSD
Requires-Python: >=3.9
License-File: LICENSE
Requires-Dist: jupyterhub >=4.1.6
Requires-Dist: ldap3 >=2.9.1
Requires-Dist: traitlets
Provides-Extra: test
Requires-Dist: pytest ; extra == 'test'
Requires-Dist: pytest-asyncio ; extra == 'test'
Requires-Dist: pytest-cov ; extra == 'test'
